ifcopenshell/__init__.py
ifcopenshell/alignment.py
ifcopenshell/draw.py
ifcopenshell/entity_instance.py
ifcopenshell/file.py
ifcopenshell/guid.py
ifcopenshell/py.typed
ifcopenshell/settings.py
ifcopenshell/sql.py
ifcopenshell/stream.py
ifcopenshell/template.py
ifcopenshell/transition_curve.py
ifcopenshell/validate.py
ifcopenshell/api/__init__.py
ifcopenshell/api/aggregate/__init__.py
ifcopenshell/api/aggregate/assign_object.py
ifcopenshell/api/aggregate/unassign_object.py
ifcopenshell/api/attribute/__init__.py
ifcopenshell/api/attribute/edit_attributes.py
ifcopenshell/api/boundary/__init__.py
ifcopenshell/api/boundary/assign_connection_geometry.py
ifcopenshell/api/boundary/copy_boundary.py
ifcopenshell/api/boundary/edit_attributes.py
ifcopenshell/api/boundary/remove_boundary.py
ifcopenshell/api/classification/__init__.py
ifcopenshell/api/classification/add_classification.py
ifcopenshell/api/classification/add_reference.py
ifcopenshell/api/classification/edit_classification.py
ifcopenshell/api/classification/edit_reference.py
ifcopenshell/api/classification/remove_classification.py
ifcopenshell/api/classification/remove_reference.py
ifcopenshell/api/constraint/__init__.py
ifcopenshell/api/constraint/add_metric.py
ifcopenshell/api/constraint/add_metric_reference.py
ifcopenshell/api/constraint/add_objective.py
ifcopenshell/api/constraint/assign_constraint.py
ifcopenshell/api/constraint/edit_metric.py
ifcopenshell/api/constraint/edit_objective.py
ifcopenshell/api/constraint/remove_constraint.py
ifcopenshell/api/constraint/remove_metric.py
ifcopenshell/api/constraint/unassign_constraint.py
ifcopenshell/api/context/__init__.py
ifcopenshell/api/context/add_context.py
ifcopenshell/api/context/edit_context.py
ifcopenshell/api/context/remove_context.py
ifcopenshell/api/control/__init__.py
ifcopenshell/api/control/assign_control.py
ifcopenshell/api/control/unassign_control.py
ifcopenshell/api/cost/__init__.py
ifcopenshell/api/cost/add_cost_item.py
ifcopenshell_ids-0.8.0.dist-info/METADATA
ifcopenshell_ids-0.8.0.dist-info/WHEEL
ifcopenshell_ids-0.8.0.dist-info/top_level.txt
ifcopenshell_ids-0.8.0.dist-info/RECORD
